{"0": "affirm", "1": "ask_academic_performance", "2": "ask_academic_risk_students", "3": "ask_academic_vulnerable_students", "4": "ask_active_students_only", "5": "ask_all_groups", "6": "ask_archivos_info", "7": "ask_attendance_stats", "8": "ask_career_info", "9": "ask_classroom_usage", "10": "ask_correlations", "11": "ask_critical_risk_students", "12": "ask_definitive_dropout_students", "13": "ask_early_warning", "14": "ask_economic_vulnerable_students", "15": "ask_encuestas_info", "16": "ask_excellent_students", "17": "ask_failing_students_only", "18": "ask_failure_analysis", "19": "ask_family_vulnerable_students", "20": "ask_forum_categories", "21": "ask_general_stats", "22": "ask_good_students", "23": "ask_grade_range_students", "24": "ask_graduated_students", "25": "ask_group_average", "26": "ask_group_info", "27": "ask_group_tutor", "28": "ask_groups_by_career", "29": "ask_groups_risk", "30": "ask_groups_without_tutor", "31": "ask_help_requests", "32": "ask_high_risk_students", "33": "ask_high_risk_students_only", "34": "ask_inactive_students", "35": "ask_low_grade_students", "36": "ask_low_grade_students_specific", "37": "ask_medium_risk_students", "38": "ask_news_views", "39": "ask_posts_by_category", "40": "ask_recommendations", "41": "ask_schedules", "42": "ask_sesiones_info", "43": "ask_socioeconomic_vulnerable_students", "44": "ask_student_by_name_or_id", "45": "ask_student_grades", "46": "ask_student_tracking", "47": "ask_students_by_career", "48": "ask_students_by_period", "49": "ask_students_by_specific_career", "50": "ask_students_extraordinary", "51": "ask_students_last_chance", "52": "ask_students_ordinary", "53": "ask_students_remedial", "54": "ask_students_without_group", "55": "ask_subjects_by_career", "56": "ask_teacher_by_name_or_id", "57": "ask_teacher_tutors", "58": "ask_teachers_by_career", "59": "ask_teachers_comparison", "60": "ask_teachers_load", "61": "ask_teachers_low_grades", "62": "ask_temporary_dropout_students", "63": "ask_top_students", "64": "ask_tutor_groups", "65": "ask_vulnerable_students", "66": "bot_challenge", "67": "deny", "68": "goodbye", "69": "greet"}